podium_lib/__init__.py
podium_lib/describe.py
podium_lib/functions.py
podium_lib/py.typed
podium_lib/utils.py
podium_lib/converters/__init__.py
podium_lib/converters/_classes.py
podium_lib/converters/dataframe/__init__.py
podium_lib/converters/dataframe/_queries.py
podium_lib/converters/dataframe/dataframe.py
podium_lib/converters/field/__init__.py
podium_lib/converters/field/_queries.py
podium_lib/converters/field/field.py
podium_lib/dataframe/__init__.py
podium_lib/dataframe/config.py
podium_lib/dataframe/dataframe.py
podium_lib/dataframe/lazyframe.py
podium_lib/model/__init__.py
podium_lib/model/field.py
podium_lib/model/model.py
podium_lib/validators/__init__.py
podium_lib/validators/_classes.py
podium_lib/validators/dataframe/__init__.py
podium_lib/validators/dataframe/_predicates.py
podium_lib/validators/dataframe/dataframe.py
podium_lib/validators/field/__init__.py
podium_lib/validators/field/_predicates.py
podium_lib/validators/field/field.py
podium_lib/validators/schema/__init__.py
podium_lib/validators/schema/_predicates.py
podium_lib/validators/schema/schema.py
podium_lib-0.1.0.dist-info/METADATA
podium_lib-0.1.0.dist-info/WHEEL
podium_lib-0.1.0.dist-info/RECORD
