Metadata-Version: 2.4
Name: podium-lib
Version: 0.1.0
Summary: Class-based data-expression framework.
Author-email: lucas-nelson-uiuc <lucas.nelson.contacts@gmail.com>
Requires-Python: >=3.10
Requires-Dist: narwhals>=1.26.0
